tf_clahe/__init__.py
tf_clahe-0.1.0.dist-info/LICENSE
tf_clahe-0.1.0.dist-info/METADATA
tf_clahe-0.1.0.dist-info/WHEEL
tf_clahe-0.1.0.dist-info/top_level.txt
tf_clahe-0.1.0.dist-info/RECORD
