Metadata-Version: 2.1
Name: tf-clahe
Version: 0.1.0
Summary: Contrast limited adaptive histogram equalization implemented in TF ops
Home-page: https://github.com/isears/tf_clahe
Author: Isaac Sears
Author-email: is6gc@virginia.edu
License: UNKNOWN
Platform: UNKNOWN
Classifier: Programming Language :: Python :: 3
Classifier: License :: OSI Approved :: MIT License
Classifier: Operating System :: OS Independent
Requires-Python: >=3.6
Requires-Dist: tensorflow (>=2.3)
Requires-Dist: tensorflow-addons (>=0.10)
